mozinstall/__init__.py
mozinstall/mozinstall.py
mozInstall-2.1.0.dist-info/METADATA
mozInstall-2.1.0.dist-info/WHEEL
mozInstall-2.1.0.dist-info/entry_points.txt
mozInstall-2.1.0.dist-info/top_level.txt
mozInstall-2.1.0.dist-info/RECORD
